faraday/__init__.py
faraday/alembic.ini
faraday/manage.py
faraday/requirements.txt
faraday/start_all.py
faraday/start_server.py
faraday/migrations/README
faraday/migrations/env.py
faraday/migrations/script.py.mako
faraday/migrations/versions/.gitignore
faraday/migrations/versions/000918b77c25_add_jira_scope.py
faraday/migrations/versions/0409e696eeec_workspace_important_flag_and_risk_.py
faraday/migrations/versions/06c48492f587_reformat_jira_issue_fields_value.py
faraday/migrations/versions/077b7c925ded_add_last_run_to_executors.py
faraday/migrations/versions/085188e0a016_create_rules_tables.py
faraday/migrations/versions/08d02214aedc_add_advanced_filter_to_executive_report_table.py
faraday/migrations/versions/0d216660da28_add_notification_table.py
faraday/migrations/versions/0ed0dab44def_add_tags_arguments_for_agent_schedule.py
faraday/migrations/versions/1145efa88414_add_warnings_to_command_model.py
faraday/migrations/versions/11560f56f480_add_target_to_action.py
faraday/migrations/versions/1574fbcf72f5_disable_several_notifications_and_add_event_enabled_flag.py
faraday/migrations/versions/15d70093d262_severities_histogram_model.py
faraday/migrations/versions/182832ed9733_add_socket_agent_sid.py
faraday/migrations/versions/18891ca61db6_add_cascade_delete_from_workspace.py
faraday/migrations/versions/1b2533cc16fe_fix_custom_fields_display_name_was_used_.py
faraday/migrations/versions/1d328f7bf643_planner_model.py
faraday/migrations/versions/1dbe9e8e4247_add_rule_execution_start_and_end_fields.py
faraday/migrations/versions/1e95dde5b9c8_cascade_on_kb.py
faraday/migrations/versions/2063ac75ffb1_workspace_summary_report.py
faraday/migrations/versions/20f3d0c2f71f_alter_table_executive_report_add_.py
faraday/migrations/versions/247a90b029f2_fix_severities_ordering.py
faraday/migrations/versions/257f6d0ad43f_add_fields_to_kb.py
faraday/migrations/versions/27d7eff884e7_divide_open_for_days.py
faradaysec-5.19.0.dist-info/licenses/AUTHORS
faradaysec-5.19.0.dist-info/licenses/LICENSE
faradaysec-5.19.0.dist-info/METADATA
faradaysec-5.19.0.dist-info/WHEEL
faradaysec-5.19.0.dist-info/entry_points.txt
faradaysec-5.19.0.dist-info/top_level.txt
faradaysec-5.19.0.dist-info/RECORD
