Metadata-Version: 2.4
Name: faradaysec
Version: 5.19.0
Summary: Open Source Collaborative Penetration Test and Vulnerability Management Platform https://www.faradaysec.com
Home-page: https://github.com/infobyte/faraday
Author: Faradaysec
Author-email: devel@faradaysec.com
Project-URL: Bug Reports, https://github.com/infobyte/faraday/issues
Project-URL: Say Thanks!, http://saythanks.io/to/faradaysec
Project-URL: Source, https://github.com/infobyte/faraday/
Keywords: security tools
Classifier: Development Status :: 5 - Production/Stable
Classifier: Intended Audience :: Information Technology
Classifier: Intended Audience :: System Administrators
Classifier: Topic :: Security
Classifier: Topic :: Software Development :: Bug Tracking
Classifier: Topic :: Software Development :: Quality Assurance
Classifier: Topic :: System :: Networking :: Monitoring
Classifier: License :: OSI Approved :: GNU General Public License v3 (GPLv3)
Classifier: Programming Language :: Python :: 3
Classifier: Programming Language :: Python :: 3.7
Classifier: Programming Language :: Python :: 3.8
Classifier: Programming Language :: Python :: 3.9
Requires-Python: >=3.7
License-File: LICENSE
License-File: AUTHORS
Requires-Dist: PyJWT>=2.3.0
Requires-Dist: werkzeug<2.1.0,>=1.0.0
Requires-Dist: autobahn>=22.7.1
Requires-Dist: alembic>=0.9.9
Requires-Dist: bcrypt<5.0.0
Requires-Dist: colorama>=0.3.9
Requires-Dist: click>=8.0.1
Requires-Dist: flask<=2.1.3,>=1.1
Requires-Dist: Flask-SQLAlchemy<=2.5.1,>=2.3.1
Requires-Dist: flask-classful<0.16,>=0.14
Requires-Dist: email_validator
Requires-Dist: validators
Requires-Dist: Flask-WTF<=1.0.1,>=0.15.1
Requires-Dist: WTForms>=2.1
Requires-Dist: flask-login<0.6.0,>=0.5.0
Requires-Dist: Flask-Security-Too<5.0.0,>=4.0.0
Requires-Dist: bleach<5.0.0,>=4.1.0
Requires-Dist: marshmallow<4.0.0,>=3.19.0
Requires-Dist: Pillow>=10.2.0
Requires-Dist: psycopg2
Requires-Dist: pgcli
Requires-Dist: cryptography>=40.0.1
Requires-Dist: pyopenssl>=23.1.1
Requires-Dist: python-dateutil>=2.6.0
Requires-Dist: requests>=2.18.4
Requires-Dist: pyasn1
Requires-Dist: service_identity>=17.0.0
Requires-Dist: SQLAlchemy<1.4.0,>=1.2.0
Requires-Dist: tqdm>=4.15.0
Requires-Dist: webargs>=7.0.0
Requires-Dist: marshmallow-sqlalchemy<0.28.1,>=0.26.1
Requires-Dist: filteralchemy-fork
Requires-Dist: filedepot<0.11.0,>=0.5.0
Requires-Dist: nplusone>=0.8.1
Requires-Dist: syslog-rfc5424-formatter>=1.1.1
Requires-Dist: simplekv>=0.13.0
Requires-Dist: Flask-KVSession-fork>=0.6.4
Requires-Dist: distro>=1.4.0
Requires-Dist: faraday-plugins<2.0.0,>=1.27.2
Requires-Dist: apispec>=6.3.0
Requires-Dist: apispec-webframeworks<=0.5.2
Requires-Dist: pyyaml
Requires-Dist: bidict==0.22.0
Requires-Dist: Flask-SocketIO>=5.0.1
Requires-Dist: pyotp>=2.6.0
Requires-Dist: Flask-Limiter<1.4.0,>=1.3.1
Requires-Dist: Flask-Mail
Requires-Dist: faraday-agent-parameters-types>=1.9.1
Requires-Dist: cvss>=3.1
Requires-Dist: celery==5.4.0
Requires-Dist: kombu==5.4.2
Requires-Dist: gevent>=22.10.2
Requires-Dist: psycogreen>=1.0.2
Requires-Dist: Flask-Celery-Helper>=1.1.0
Requires-Dist: redis>=4.3.4
Requires-Dist: gevent-websocket>=0.10.1
Requires-Dist: sh
Requires-Dist: elasticsearch>=7.16.3
Requires-Dist: croniter>=0.3.30
Provides-Extra: dev
Requires-Dist: check-manifest; extra == "dev"
Provides-Extra: test
Requires-Dist: coverage; extra == "test"
Dynamic: author
Dynamic: author-email
Dynamic: classifier
Dynamic: description
Dynamic: description-content-type
Dynamic: home-page
Dynamic: keywords
Dynamic: license-file
Dynamic: project-url
Dynamic: provides-extra
Dynamic: requires-dist
Dynamic: requires-python
Dynamic: summary
